frace-0.1.0.dist-info/METADATA
frace-0.1.0.dist-info/WHEEL
frace-0.1.0.dist-info/entry_points.txt
frace/__init__.py
frace/main.py
frace/models.py
frace/utils.py
frace-0.1.0.dist-info/RECORD
