Metadata-Version: 2.1
Name: frace
Version: 0.1.0
Summary: F-Race, bunch of python awaitables racing to get fastest response considering exceptions, retries and backoffs
Author-Email: Harishankar Kumar <hsk@althire.ai>
License: MIT
Project-URL: Homepage, https://github.com/searchX/frace
Requires-Python: >=3.9
Requires-Dist: pydantic>=2.10.5
